LICENSE.txt
wavespectra/__init__.py
wavespectra/specarray.py
wavespectra/specdataset.py
wavespectra/specpart.so
wavespectra/construct/__init__.py
wavespectra/construct/helpers.py
wavespectra/construct/jonswap.py
wavespectra/construct/ochihubble.py
wavespectra/core/__init__.py
wavespectra/core/attributes.py
wavespectra/core/attributes.yml
wavespectra/core/misc.py
wavespectra/core/swan.py
wavespectra/input/__init__.py
wavespectra/input/dictionary.py
wavespectra/input/json.py
wavespectra/input/netcdf.py
wavespectra/input/octopus.py
wavespectra/input/swan.py
wavespectra/input/ww3.py
wavespectra/input/ww3_msl.py
wavespectra/output/__init__.py
wavespectra/output/json.py
wavespectra/output/netcdf.py
wavespectra/output/octopus.py
wavespectra/output/swan.py
wavespectra/output/ww3.py
wavespectra/output/ww3_msl.py
wavespectra-0.1.2.dist-info/DESCRIPTION.rst
wavespectra-0.1.2.dist-info/METADATA
wavespectra-0.1.2.dist-info/RECORD
wavespectra-0.1.2.dist-info/WHEEL
wavespectra-0.1.2.dist-info/metadata.json
wavespectra-0.1.2.dist-info/top_level.txt
