Metadata-Version: 2.0
Name: wavespectra
Version: 0.1.2
Summary: Ocean wave spectra tools
Home-page: http://github.com/metocean/wavespectra
Author: MetOcean Solutions
Author-email: r.guedes@metocean.co.nz
License: MIT
Project-URL: Bug Reports, https://github.com/metocean/wavespectra/issues
Project-URL: Source, https://github.com/metocean/wavespectra
Project-URL: Funding, http://www.metocean.co.nz
Project-URL: Say Thanks!, http://www.metocean.co.nz
Keywords: wave spectra ocean xarray statistics analysis
Platform: any
Classifier: Development Status :: 4 - Beta
Classifier: Intended Audience :: Science/Research
Classifier: License :: OSI Approved :: MIT License
Classifier: Programming Language :: Python :: 2
Classifier: Programming Language :: Python :: 2.7
Classifier: Topic :: Scientific/Engineering
Classifier: Topic :: Scientific/Engineering :: Physics
Classifier: Topic :: Scientific/Engineering :: Visualization
Requires-Python: >=2.7, <3
Provides-Extra: extra
Requires-Dist: attrdict
Requires-Dist: dask
Requires-Dist: numpy
Requires-Dist: pandas
Requires-Dist: pyaml
Requires-Dist: python-dateutil
Requires-Dist: scipy
Requires-Dist: sortedcontainers
Requires-Dist: toolz
Requires-Dist: xarray (>=0.10.0)
Provides-Extra: extra
Requires-Dist: dbfread; extra == 'extra'
Requires-Dist: netCDF4; extra == 'extra'
Requires-Dist: sympy; extra == 'extra'
